Metadata-Version: 2.1
Name: fdtdz
Version: 1.1.2
Summary: Fast, scalable, and free photonic simulation
Home-page: https://github.com/spinsphotonics/fdtdz
Author: Jesse Lu
Author-email: jesselu@spinsphotonics.com
License: MIT
Platform: UNKNOWN
Provides-Extra: test
License-File: LICENSE
